{
  "configVersion": 1,
  "timestamp": 1734953677593,
  "index": "/msk/index.html",
  "assetGroups": [
    {
      "name": "app",
      "installMode": "prefetch",
      "updateMode": "prefetch",
      "cacheQueryOptions": {
        "ignoreVary": true
      },
      "urls": [
        "/msk/chunk-2R6CW7ES.js",
        "/msk/chunk-35HVQD6C.js",
        "/msk/chunk-3BAOVXAY.js",
        "/msk/chunk-3JWV32N7.js",
        "/msk/chunk-3PNVHZM2.js",
        "/msk/chunk-3THCIBOJ.js",
        "/msk/chunk-4AJ4A43T.js",
        "/msk/chunk-4KXBJWPX.js",
        "/msk/chunk-4QKILKOO.js",
        "/msk/chunk-54M27S7E.js",
        "/msk/chunk-5O6KMM72.js",
        "/msk/chunk-5QQ6W4LY.js",
        "/msk/chunk-5TBKSVUW.js",
        "/msk/chunk-5WVQGO2Q.js",
        "/msk/chunk-6SFO5KBL.js",
        "/msk/chunk-6TFIXF7N.js",
        "/msk/chunk-7AXCTRCT.js",
        "/msk/chunk-7MAFH4G7.js",
        "/msk/chunk-A7PCECPO.js",
        "/msk/chunk-BRYUOZX2.js",
        "/msk/chunk-BWITEVXC.js",
        "/msk/chunk-CSRKN4UR.js",
        "/msk/chunk-CWFLNCG7.js",
        "/msk/chunk-D5RFYHXS.js",
        "/msk/chunk-D7IHU2TB.js",
        "/msk/chunk-DWMY2D5S.js",
        "/msk/chunk-DYIREUOE.js",
        "/msk/chunk-DYXZEK2U.js",
        "/msk/chunk-EB6ARYXX.js",
        "/msk/chunk-EUHEEEBK.js",
        "/msk/chunk-FF7LV7NV.js",
        "/msk/chunk-GIHHEAWC.js",
        "/msk/chunk-GUKA36SK.js",
        "/msk/chunk-HDLVQ5NJ.js",
        "/msk/chunk-HRWTSGCQ.js",
        "/msk/chunk-HTZE5BF4.js",
        "/msk/chunk-HXPADMA4.js",
        "/msk/chunk-I3ROGWBB.js",
        "/msk/chunk-IFOGAWSS.js",
        "/msk/chunk-IL6GJSRZ.js",
        "/msk/chunk-IRIU66MO.js",
        "/msk/chunk-JR4PG74O.js",
        "/msk/chunk-K5KM7A2L.js",
        "/msk/chunk-KSMBIED2.js",
        "/msk/chunk-LIJZS6AT.js",
        "/msk/chunk-MTPBTYZI.js",
        "/msk/chunk-O47SJUOT.js",
        "/msk/chunk-OL54RBMB.js",
        "/msk/chunk-P37J7QNG.js",
        "/msk/chunk-PFAPKXYX.js",
        "/msk/chunk-PQIF4GUV.js",
        "/msk/chunk-QQNSMRXZ.js",
        "/msk/chunk-RRCSQMSS.js",
        "/msk/chunk-S3LXHWOE.js",
        "/msk/chunk-TA5FHACR.js",
        "/msk/chunk-URZL6SS3.js",
        "/msk/chunk-UTAYEAE4.js",
        "/msk/chunk-V4WTMKZN.js",
        "/msk/chunk-VPIVYREY.js",
        "/msk/chunk-VPOB5AJW.js",
        "/msk/chunk-WJO5AUEC.js",
        "/msk/chunk-X5UW3ZGK.js",
        "/msk/chunk-XJ3RBRC2.js",
        "/msk/chunk-YBO4MF7V.js",
        "/msk/chunk-YHI574TZ.js",
        "/msk/chunk-YXOBKGFO.js",
        "/msk/chunk-Z6BJZVDG.js",
        "/msk/favicon.ico",
        "/msk/index.html",
        "/msk/main-W7WTF6IC.js",
        "/msk/manifest.webmanifest",
        "/msk/polyfills-FFHMD2TL.js",
        "/msk/styles-55JK5LYL.css"
      ],
      "patterns": []
    },
    {
      "name": "assets",
      "installMode": "lazy",
      "updateMode": "prefetch",
      "cacheQueryOptions": {
        "ignoreVary": true
      },
      "urls": [
        "/msk/assets/api/navigation.json",
        "/msk/assets/api/user.json",
        "/msk/assets/fonts/IRANSansX/fontiran.css",
        "/msk/assets/fonts/IRANSansX/woff/IRANSansX-Black.woff",
        "/msk/assets/fonts/IRANSansX/woff/IRANSansX-Bold.woff",
        "/msk/assets/fonts/IRANSansX/woff/IRANSansX-DemiBold.woff",
        "/msk/assets/fonts/IRANSansX/woff/IRANSansX-ExtraBold.woff",
        "/msk/assets/fonts/IRANSansX/woff/IRANSansX-Light.woff",
        "/msk/assets/fonts/IRANSansX/woff/IRANSansX-Medium.woff",
        "/msk/assets/fonts/IRANSansX/woff/IRANSansX-Regular.woff",
        "/msk/assets/fonts/IRANSansX/woff/IRANSansX-Thin.woff",
        "/msk/assets/fonts/IRANSansX/woff/IRANSansX-UltraLight.woff",
        "/msk/assets/fonts/IRANSansX/woff2/IRANSansX-Black.woff2",
        "/msk/assets/fonts/IRANSansX/woff2/IRANSansX-Bold.woff2",
        "/msk/assets/fonts/IRANSansX/woff2/IRANSansX-DemiBold.woff2",
        "/msk/assets/fonts/IRANSansX/woff2/IRANSansX-ExtraBold.woff2",
        "/msk/assets/fonts/IRANSansX/woff2/IRANSansX-Light.woff2",
        "/msk/assets/fonts/IRANSansX/woff2/IRANSansX-Medium.woff2",
        "/msk/assets/fonts/IRANSansX/woff2/IRANSansX-Regular.woff2",
        "/msk/assets/fonts/IRANSansX/woff2/IRANSansX-Thin.woff2",
        "/msk/assets/fonts/IRANSansX/woff2/IRANSansX-UltraLight.woff2",
        "/msk/assets/i18n/en.json",
        "/msk/assets/i18n/fa.json",
        "/msk/assets/icons/heroicons-outline.svg",
        "/msk/assets/icons/heroicons-solid.svg",
        "/msk/assets/icons/icon-128x128.png",
        "/msk/assets/icons/icon-144x144.png",
        "/msk/assets/icons/icon-152x152.png",
        "/msk/assets/icons/icon-192x192.png",
        "/msk/assets/icons/icon-384x384.png",
        "/msk/assets/icons/icon-512x512.png",
        "/msk/assets/icons/icon-72x72.png",
        "/msk/assets/icons/icon-96x96.png",
        "/msk/assets/images/flags/en.svg",
        "/msk/assets/images/flags/fa.svg",
        "/msk/assets/images/logo/logo.svg",
        "/msk/assets/images/profiles/profile.jpg",
        "/msk/assets/styles/splash-screen.css"
      ],
      "patterns": []
    }
  ],
  "dataGroups": [],
  "hashTable": {
    "/msk/assets/api/navigation.json": "499012239f841a24a5600f89778e413c41a2f681",
    "/msk/assets/api/user.json": "10f99dc71008f2ad4576773ced33e3a1a5ff1558",
    "/msk/assets/fonts/IRANSansX/fontiran.css": "78f350cb377c096ea9750285be49bec9787cc11f",
    "/msk/assets/fonts/IRANSansX/woff/IRANSansX-Black.woff": "6a4e28abe21634fd72034442fa4b6a667abb5a39",
    "/msk/assets/fonts/IRANSansX/woff/IRANSansX-Bold.woff": "d7de9acd4788081b657be1744b70457545d682a8",
    "/msk/assets/fonts/IRANSansX/woff/IRANSansX-DemiBold.woff": "954c15456c235b4d25800e8fa36e5e73e75ecb89",
    "/msk/assets/fonts/IRANSansX/woff/IRANSansX-ExtraBold.woff": "8e272755d2b9568e08d4f17ad8e2f9eda05ad752",
    "/msk/assets/fonts/IRANSansX/woff/IRANSansX-Light.woff": "cd86b64ccf30c567c6694b841ab01c9d10724a2b",
    "/msk/assets/fonts/IRANSansX/woff/IRANSansX-Medium.woff": "e636a1159555ea7501cd721d71d8b0913f73c0b8",
    "/msk/assets/fonts/IRANSansX/woff/IRANSansX-Regular.woff": "e6f4b6c487f3fa357a1f5652a6efe69758360be1",
    "/msk/assets/fonts/IRANSansX/woff/IRANSansX-Thin.woff": "539363c53dd2418caa8de1bf1ad955d64c3ddc5e",
    "/msk/assets/fonts/IRANSansX/woff/IRANSansX-UltraLight.woff": "ca143ada430d7791531a70228e43179b5efd7136",
    "/msk/assets/fonts/IRANSansX/woff2/IRANSansX-Black.woff2": "dc772d0a6a6f11413731c006f62a90d477218212",
    "/msk/assets/fonts/IRANSansX/woff2/IRANSansX-Bold.woff2": "0874d4781536db75bb6221e2743464634f5a1a4d",
    "/msk/assets/fonts/IRANSansX/woff2/IRANSansX-DemiBold.woff2": "de4525a19ce1ef39b76724c09325accce33cd54d",
    "/msk/assets/fonts/IRANSansX/woff2/IRANSansX-ExtraBold.woff2": "d4de8799e6b95959f184448e0551fcfe3eb6e8ff",
    "/msk/assets/fonts/IRANSansX/woff2/IRANSansX-Light.woff2": "02044f12757c015c61c98d3436e69cb4b56d4978",
    "/msk/assets/fonts/IRANSansX/woff2/IRANSansX-Medium.woff2": "1727ace11d2ac3b3fe541697ebe071dbc9e7e906",
    "/msk/assets/fonts/IRANSansX/woff2/IRANSansX-Regular.woff2": "fc3cdf42c3b8ab7dc9d99dafd8920ebf479e585e",
    "/msk/assets/fonts/IRANSansX/woff2/IRANSansX-Thin.woff2": "2702fc5419fd1ece0f7a7e13533647e63d9b5ac4",
    "/msk/assets/fonts/IRANSansX/woff2/IRANSansX-UltraLight.woff2": "abb8722b68d3898ef456a59593f6f30402138438",
    "/msk/assets/i18n/en.json": "4559e9af52974dfc08dc74db1c0ef4907a8e075e",
    "/msk/assets/i18n/fa.json": "ce83d58eca9c3bc8d2feb6b3c6713161a90aa2ea",
    "/msk/assets/icons/heroicons-outline.svg": "02b30c181518eb941d8fcec6dff9af1f4d085ed4",
    "/msk/assets/icons/heroicons-solid.svg": "33909d2bf1892f251ad7904e7552e1ab3fe20e46",
    "/msk/assets/icons/icon-128x128.png": "f912963bdc6d5a38d8f1dd0afbaab2ce8d657acb",
    "/msk/assets/icons/icon-144x144.png": "b155fd5f2fd5d2ea7760721063003c4cd95fd783",
    "/msk/assets/icons/icon-152x152.png": "eae6e0f0c8afb8aaae339e2a569b43e9238e5e6c",
    "/msk/assets/icons/icon-192x192.png": "15c4180454633880d98674aa7394656196c91584",
    "/msk/assets/icons/icon-384x384.png": "94a915751ef6c9282df9aea405ad679230631814",
    "/msk/assets/icons/icon-512x512.png": "1de182f76f7329dfa8f9fcdd1fdcdd695bea6a99",
    "/msk/assets/icons/icon-72x72.png": "aa88a6096bd973be7f6d7a5489bfa6bc2463f8c4",
    "/msk/assets/icons/icon-96x96.png": "7fb8f59c30ce2ff12c700321a0b39e14b3dc8f95",
    "/msk/assets/images/flags/en.svg": "494ca7edf72a966dcd206c8cb706d976a6f6ccd4",
    "/msk/assets/images/flags/fa.svg": "d2b7e47c0f9ad6befc4cf6cc926e800c619deda7",
    "/msk/assets/images/logo/logo.svg": "255a3fb20e25a6f42cde1b9c08be22d33f53cad0",
    "/msk/assets/images/profiles/profile.jpg": "1b4487f6e59d7710344332d81849041578277dfd",
    "/msk/assets/styles/splash-screen.css": "2303a139d5ba24512b897a69f8e340cd99a52696",
    "/msk/chunk-2R6CW7ES.js": "8d967f48bdb35b567f73ae15e3851ceb6330819e",
    "/msk/chunk-35HVQD6C.js": "c8e879f896b0a98f45d30ea98a80b2165b234779",
    "/msk/chunk-3BAOVXAY.js": "734d749a09d819bd499d31ba85222833e6e70450",
    "/msk/chunk-3JWV32N7.js": "849315484ca781812db01a184878b0afce4d59a7",
    "/msk/chunk-3PNVHZM2.js": "e18c7204a63925fd5c8319d39f47b8ada060f12f",
    "/msk/chunk-3THCIBOJ.js": "6248abc580db6967740497971bf8c8313d36c77d",
    "/msk/chunk-4AJ4A43T.js": "b6c2aba4c6ccd497562183d1f70553ed2fa99210",
    "/msk/chunk-4KXBJWPX.js": "403530c7d2c6d5be0b8032c2889d6ec54d511b64",
    "/msk/chunk-4QKILKOO.js": "b01d7d07146e14432d8b42e7f3490e95bd9d07c5",
    "/msk/chunk-54M27S7E.js": "e567d7bdb3bbbc202eb7e35de0e5266f8e4427bc",
    "/msk/chunk-5O6KMM72.js": "693167ec97bef8e392fef33f4f196f14cf2e7b53",
    "/msk/chunk-5QQ6W4LY.js": "909c8f5f4b6b7d6b0599d4f440748c0e6cf922fb",
    "/msk/chunk-5TBKSVUW.js": "5a0577276c45253b792289b2345f6c6850656e19",
    "/msk/chunk-5WVQGO2Q.js": "441aa5e4965964f5fdaf187f8d187f8ea0656599",
    "/msk/chunk-6SFO5KBL.js": "6d35d12afc988e47bf6739652cc2b32003aa30d8",
    "/msk/chunk-6TFIXF7N.js": "1802839651494ba9ff95ebaa853b517cc27d6957",
    "/msk/chunk-7AXCTRCT.js": "55c505b85624cd0c3af93732e2541cc2b3427f1f",
    "/msk/chunk-7MAFH4G7.js": "e76348255e9c9921e822d335064fea39cc644ada",
    "/msk/chunk-A7PCECPO.js": "a704cf070b6ccbe11c70be62a4166a35e999677e",
    "/msk/chunk-BRYUOZX2.js": "34d5c464bad6d1cc8b79c732bed791391367c37e",
    "/msk/chunk-BWITEVXC.js": "849315484ca781812db01a184878b0afce4d59a7",
    "/msk/chunk-CSRKN4UR.js": "d674cff22c774eee864f5777ec2b0a7ed6c424f6",
    "/msk/chunk-CWFLNCG7.js": "e195321c6cd5e9e6fc5f957a05ea4a22e3555f48",
    "/msk/chunk-D5RFYHXS.js": "98044cc560e188f5b9800260965ce3418c615e17",
    "/msk/chunk-D7IHU2TB.js": "cb086dd14162d4912f893a91a5ef91e976ba3acd",
    "/msk/chunk-DWMY2D5S.js": "4f38b188005dfccf0b471dec540b6db4cab8390f",
    "/msk/chunk-DYIREUOE.js": "ea07e6edbc0e2247cf5236eb8b2b91a1b39ff4ac",
    "/msk/chunk-DYXZEK2U.js": "6c885f8bfefd9eb3b43a6ab83a6beb6b55c27a0a",
    "/msk/chunk-EB6ARYXX.js": "e872bcd1fba3b5070d1ffbfdd4871b83f039efde",
    "/msk/chunk-EUHEEEBK.js": "63b7b235b854227067c7f7ad5e12bb6a3cc93ae7",
    "/msk/chunk-FF7LV7NV.js": "ced35e62a55e7a5aa23320817eca6299336dcec1",
    "/msk/chunk-GIHHEAWC.js": "1e44973c1b0e74edbb62cb4d028a2aa3aa73aefa",
    "/msk/chunk-GUKA36SK.js": "5e167782a04700fbda556032843a7c6c4a7a488b",
    "/msk/chunk-HDLVQ5NJ.js": "53dbfa6eb7b5c2a988e4eedb784befcf0882e56e",
    "/msk/chunk-HRWTSGCQ.js": "4dacf1b19cc0b24100109c4542aeff0cc5f7413c",
    "/msk/chunk-HTZE5BF4.js": "4036bc67f47b07588de1eb17d069bb1b7263d627",
    "/msk/chunk-HXPADMA4.js": "c6e84349b9c2619a510897a3551ac497c40e18e3",
    "/msk/chunk-I3ROGWBB.js": "f5a3d2258d2074151587703f32731188f33458d0",
    "/msk/chunk-IFOGAWSS.js": "fa53ddad1b12eb560c142b7ae702bd39440bcf1c",
    "/msk/chunk-IL6GJSRZ.js": "748f0df02993c7d908ccc9e62472e70b2dc94be7",
    "/msk/chunk-IRIU66MO.js": "53eea11c61aeeb3eff0df54228fc31c009dbe610",
    "/msk/chunk-JR4PG74O.js": "849315484ca781812db01a184878b0afce4d59a7",
    "/msk/chunk-K5KM7A2L.js": "2505d1086e80ca5a537112892ff7cdeca859bba1",
    "/msk/chunk-KSMBIED2.js": "5a3df860c50589bce19aea405dbb0e11bf09826a",
    "/msk/chunk-LIJZS6AT.js": "06d67c5c7800edce325b7b3aeb9e7e97ad58d697",
    "/msk/chunk-MTPBTYZI.js": "747bd7abe59fd70475b0a1c323c8c9b598dc5e72",
    "/msk/chunk-O47SJUOT.js": "d533b8c73a225817faef598349352b2f82ea8830",
    "/msk/chunk-OL54RBMB.js": "7880875902cf57cb5fdc5fffdd94785a3913571b",
    "/msk/chunk-P37J7QNG.js": "752cb22b145adbe7a116d7b542ce0981be5a3df2",
    "/msk/chunk-PFAPKXYX.js": "e71c120777dae6d89c24f8d75f346b3f02aa0add",
    "/msk/chunk-PQIF4GUV.js": "a6501ebdeff062efae9ccd4f330ea080fa0bc369",
    "/msk/chunk-QQNSMRXZ.js": "4fa0c0521bc7e7fc51897dd613d99f4e0bdab377",
    "/msk/chunk-RRCSQMSS.js": "d9eca159721c742182a6571543a28740388428da",
    "/msk/chunk-S3LXHWOE.js": "9baa3ef2308c979bcae5883b60f021e5f23140cd",
    "/msk/chunk-TA5FHACR.js": "b2165e230dc1ab8ce536563f8faecd5c6d055e85",
    "/msk/chunk-URZL6SS3.js": "8d8eaedd13db73da7c8e873bc74164a892ccf085",
    "/msk/chunk-UTAYEAE4.js": "51a5af951b168060e0126eb4c4bd00c811b78d92",
    "/msk/chunk-V4WTMKZN.js": "290e01933738632aeb9d0bb3e195ec24263a0037",
    "/msk/chunk-VPIVYREY.js": "090804a9bfda54df5fa9a5286064a4686117602d",
    "/msk/chunk-VPOB5AJW.js": "57b57831935e66c49826f84ab0b2a3ab08afe48b",
    "/msk/chunk-WJO5AUEC.js": "eb0aec5f28a90e8eda6e57cb356a6aad9557efa7",
    "/msk/chunk-X5UW3ZGK.js": "76f851fee9abbc9bafa29fa3bff8bf6948b56d3f",
    "/msk/chunk-XJ3RBRC2.js": "be168100ebf2f76bc710b4955d0f9bb89c6c204f",
    "/msk/chunk-YBO4MF7V.js": "ef6bdd4ac03a59c9c4d45038ac503d4792a16065",
    "/msk/chunk-YHI574TZ.js": "169171f862d230cae1d8d42555338e7f79a76e9d",
    "/msk/chunk-YXOBKGFO.js": "849315484ca781812db01a184878b0afce4d59a7",
    "/msk/chunk-Z6BJZVDG.js": "fc878e0f35edc4236736d9d880f9b2ae3f5a13ee",
    "/msk/favicon.ico": "4e23d0f9b6ddaf3c9ddef90dbaed2342941297b5",
    "/msk/index.html": "28163b0d79988a89340d0a0f2fa23bc5876e8ca3",
    "/msk/main-W7WTF6IC.js": "fec45b2b0746e68fd3bf8521133a16ede1fad573",
    "/msk/manifest.webmanifest": "226afe2cdeef08337bca2fbd449d89744d999c57",
    "/msk/polyfills-FFHMD2TL.js": "f49b49a155bc7d192db62a4c15d0a612b460a667",
    "/msk/styles-55JK5LYL.css": "c176b68ab0ebb9be28fc5c158e995c2f5ff16d0f"
  },
  "navigationUrls": [
    {
      "positive": true,
      "regex": "^\\/.*$"
    },
    {
      "positive": false,
      "regex": "^\\/(?:.+\\/)?[^/]*\\.[^/]*$"
    },
    {
      "positive": false,
      "regex": "^\\/(?:.+\\/)?[^/]*__[^/]*$"
    },
    {
      "positive": false,
      "regex": "^\\/(?:.+\\/)?[^/]*__[^/]*\\/.*$"
    }
  ],
  "navigationRequestStrategy": "performance"
}